wireshark_fieldbus_io/__init__.py
wireshark_fieldbus_io/enums_types.py
wireshark_fieldbus_io/packet_reader.py
wireshark_fieldbus_io/utils.py
wireshark_fieldbus_io-0.2.1.dist-info/LICENSE
wireshark_fieldbus_io-0.2.1.dist-info/METADATA
wireshark_fieldbus_io-0.2.1.dist-info/WHEEL
wireshark_fieldbus_io-0.2.1.dist-info/top_level.txt
wireshark_fieldbus_io-0.2.1.dist-info/RECORD
