Metadata-Version: 2.1
Name: wireshark_fieldbus_io
Version: 0.2.1
Summary: Extract fieldbus IO data from Wireshark capture files.
Author: mrBrutus
License: MIT License
Project-URL: Repository, https://github.com/mrBrutus/wireshark_fieldbus_io.git
Project-URL: Changelog, https://github.com/mrBrutus/wireshark_fieldbus_io/blob/main/CHANGELOG.md
Project-URL: Issues, https://github.com/mrBrutus/wireshark_fieldbus_io/issues
Classifier: Development Status :: 3 - Alpha
Classifier: Intended Audience :: Developers
Classifier: Intended Audience :: Information Technology
Classifier: Topic :: System :: Networking
Classifier: License :: OSI Approved :: MIT License
Classifier: Programming Language :: Python :: 3
Requires-Python: >=3.12
License-File: LICENSE
Requires-Dist: pyshark
